{
   "eventType":"com.okta.event_hook",
   "eventTypeVersion":"1.0",
   "cloudEventsVersion":"0.1",
   "source":"https://ericlynchdemo007.oktapreview.com/api/v1/eventHooks/whotdgtc4lQ3V32Ld0h7",
   "eventId":"89a1b5f1-1c0c-466b-a15d-b2fdc0392d6c",
   "data":{
      "events":[
         {
            "uuid":"417f9f07-e95b-11ea-8700-7b3b38522311",
            "published":"2020-08-28T18:21:13.840Z",
            "eventType":"user.account.update_profile",
            "version":"0",
            "displayMessage":"Update user profile for Okta",
            "severity":"INFO",
            "client":{
               "userAgent":{
                  "rawUserAgent":"Mozilla/5.0 (Windows NT 10.0; Win64; x64) AppleWebKit/537.36 (KHTML, like Gecko) Chrome/84.0.4147.135 Safari/537.36",
                  "os":"Windows 10",
                  "browser":"CHROME"
               },
               "zone":"null",
               "device":"Computer",
               "ipAddress":"73.184.245.132",
               "geographicalContext":{
                  "city":"Woodstock",
                  "state":"Georgia",
                  "country":"United States",
                  "postalCode":"30188",
                  "geolocation":{
                     "lat":34.1078,
                     "lon":-84.5026
                  }
               },
               "ipChain":[
                  {
                     "ip":"73.184.245.132",
                     "geographicalContext":{
                        "city":"Woodstock",
                        "state":"Georgia",
                        "country":"United States",
                        "postalCode":"30188",
                        "geolocation":{
                           "lat":34.1078,
                           "lon":-84.5026
                        }
                     },
                     "version":"V4"
                  }
               ]
            },
            "actor":{
               "id":"00up6ownmvRBJ1UHX0h7",
               "type":"User",
               "alternateId":"oktatraining@okta.com",
               "displayName":"Class Admin"
            },
            "outcome":{
               "result":"SUCCESS"
            },
            "target":[
               {
                  "id":"00uslwdxtxUswTOSv0h7",
                  "type":"User",
                  "alternateId":"igor.dean@oktaice.com",
                  "displayName":"Igor Dean"
               }
            ],
            "transaction":{
               "type":"WEB",
               "id":"X0lLGaGqITYqymQoKXs0twAAFuw",
               "detail":{
                  
               }
            },
            "debugContext":{
               "debugData":{
                  "requestId":"X0lLGaGqITYqymQoKXs0twAAFuw",
                  "threatSuspected":"false",
                  "requestUri":"/api/v1/users/00uslwdxtxUswTOSv0h7",
                  "changedAttributes":"middleName",
                  "targetEventHookIds":"whot55n4h5ApEmWvZ0h7,whotdgtc4lQ3V32Ld0h7",
                  "url":"/api/v1/users/00uslwdxtxUswTOSv0h7?"
               }
            },
            "legacyEventType":"core.user.config.profile_update.success",
            "authenticationContext":{
               "authenticationStep":0,
               "externalSessionId":"102O8M3QR27QByvuMhT8KiIVA"
            },
            "securityContext":{
               
            }
         }
      ]
   },
   "eventTime":"2020-08-28T18:21:20.408Z",
   "contentType":"application/json"
}